{
  "id": "0417_2023_s_1",
  "subject": "ICT 0417",
  "year": 2023,
  "season": "May June",
  "variant": 1,
  "totalMarks": 68,
  "duration": 90,
  "questions": [
    {
      "number": 1,
      "parts": [
        {
          "id": "1a",
          "text": "............................................................................................................................................... 2................................................................................................................................................ [2] 06_0417_11_2023_1.9 ©UCLES20232 Describethepurposeofawebbrowser. 4 ........................................................................................................................................... ........................................................................................................................................... ........................................................................................................................................... ...........................................................................................................................................",
          "marks": 2,
          "level": 1,
          "parentId": "1"
        },
        {
          "id": "1b",
          "text": "............................................................................................................................................... 2................................................................................................................................................ [2] 06_0417_11_2023_1.9 ©UCLES20232 Describethepurposeofawebbrowser. ........................................................................................................................................... ........................................................................................................................................... ........................................................................................................................................... ...........................................................................................................................................",
          "marks": 2,
          "level": 1,
          "parentId": "1"
        },
        {
          "id": "1a",
          "text": "............................................................................................................................................... 2................................................................................................................................................ [2] 06_0417_11_2023_1.9 ©UCLES20232 Describethepurposeofawebbrowser. ...........................................................................................................................................",
          "marks": 1,
          "level": 1,
          "parentId": "1"
        },
        {
          "id": "1b",
          "text": "............................................................................................................................................... 2................................................................................................................................................ [2] 06_0417_11_2023_1.9 ©UCLES20232 Describethepurposeofawebbrowser. ...........................................................................................................................................",
          "marks": 1,
          "level": 1,
          "parentId": "1"
        },
        {
          "id": "1c",
          "text": "............................................................................................................................................... 2................................................................................................................................................ [2] 06_0417_11_2023_1.9 ©UCLES20232 Describethepurposeofawebbrowser. ...........................................................................................................................................",
          "marks": 1,
          "level": 1,
          "parentId": "1"
        },
        {
          "id": "1d",
          "text": "............................................................................................................................................... 2................................................................................................................................................ [2] 06_0417_11_2023_1.9 ©UCLES20232 Describethepurposeofawebbrowser. ........................................................................................................................................... ...........................................................................................................................................",
          "marks": 1,
          "level": 1,
          "parentId": "1"
        },
        {
          "id": "1a",
          "text": "............................................................................................................................................... 2................................................................................................................................................ [2] 06_0417_11_2023_1.9 ©UCLES20232 Describethepurposeofawebbrowser. ........................................................................................................................................... ........................................................................................................................................... ........................................................................................................................................... ........................................................................................................................................... ........................................................................................................................................... ........................................................................................................................................... ........................................................................................................................................... ........................................................................................................................................... ........................................................................................................................................... ........................................................................................................................................... ........................................................................................................................................... ...........................................................................................................................................",
          "marks": 6,
          "level": 1,
          "parentId": "1"
        },
        {
          "id": "1b",
          "text": "............................................................................................................................................... 2................................................................................................................................................ [2] 06_0417_11_2023_1.9 ©UCLES20232 Describethepurposeofawebbrowser. 1........................................................................................................................................ 2........................................................................................................................................",
          "marks": 2,
          "level": 1,
          "parentId": "1"
        },
        {
          "id": "1a",
          "text": "............................................................................................................................................... 2................................................................................................................................................ [2] 06_0417_11_2023_1.9 ©UCLES20232 Describethepurposeofawebbrowser. 1........................................................................................................................................ 2........................................................................................................................................ 3........................................................................................................................................",
          "marks": 3,
          "level": 1,
          "parentId": "1"
        },
        {
          "id": "1b",
          "text": "............................................................................................................................................... 2................................................................................................................................................ [2] 06_0417_11_2023_1.9 ©UCLES20232 Describethepurposeofawebbrowser. ........................................................................................................................................... ........................................................................................................................................... ........................................................................................................................................... ........................................................................................................................................... ........................................................................................................................................... ........................................................................................................................................... ........................................................................................................................................... ...........................................................................................................................................",
          "marks": 4,
          "level": 1,
          "parentId": "1"
        },
        {
          "id": "1c",
          "text": "............................................................................................................................................... 2................................................................................................................................................ [2] 06_0417_11_2023_1.9 ©UCLES20232 Describethepurposeofawebbrowser. ........................................................................................................................................... ........................................................................................................................................... ........................................................................................................................................... ........................................................................................................................................... ........................................................................................................................................... ........................................................................................................................................... ........................................................................................................................................... ........................................................................................................................................... ........................................................................................................................................... ........................................................................................................................................... ........................................................................................................................................... ...........................................................................................................................................",
          "marks": 6,
          "level": 1,
          "parentId": "1"
        },
        {
          "id": "1a",
          "text": "............................................................................................................................................... 2................................................................................................................................................ [2] 06_0417_11_2023_1.9 ©UCLES20232 Describethepurposeofawebbrowser. 8 ........................................................................................................................................... ........................................................................................................................................... ........................................................................................................................................... ........................................................................................................................................... ........................................................................................................................................... ........................................................................................................................................... ........................................................................................................................................... ........................................................................................................................................... ........................................................................................................................................... ........................................................................................................................................... ........................................................................................................................................... ...........................................................................................................................................",
          "marks": 6,
          "level": 1,
          "parentId": "1"
        },
        {
          "id": "1b",
          "text": "............................................................................................................................................... 2................................................................................................................................................ [2] 06_0417_11_2023_1.9 ©UCLES20232 Describethepurposeofawebbrowser. 1........................................................................................................................................ 2........................................................................................................................................",
          "marks": 2,
          "level": 1,
          "parentId": "1"
        },
        {
          "id": "1a",
          "text": "............................................................................................................................................... 2................................................................................................................................................ [2] 06_0417_11_2023_1.9 ©UCLES20232 Describethepurposeofawebbrowser. 9 Explainthedifferencesbetweenanabsolutefilepathandarelativefilepath.",
          "marks": 1,
          "level": 1,
          "parentId": "1"
        },
        {
          "id": "1iii",
          "text": "............................................................................................................................................... 2................................................................................................................................................ [2] 06_0417_11_2023_1.9 ©UCLES20232 Describethepurposeofawebbrowser. ................................................................................................................................ ................................................................................................................................",
          "marks": 1,
          "level": 2,
          "parentId": "1i"
        },
        {
          "id": "1b",
          "text": "............................................................................................................................................... 2................................................................................................................................................ [2] 06_0417_11_2023_1.9 ©UCLES20232 Describethepurposeofawebbrowser. ........................................................................................................................................... ........................................................................................................................................... ........................................................................................................................................... ........................................................................................................................................... ........................................................................................................................................... ........................................................................................................................................... ........................................................................................................................................... ...........................................................................................................................................",
          "marks": 4,
          "level": 1,
          "parentId": "1"
        },
        {
          "id": "1a",
          "text": "............................................................................................................................................... 2................................................................................................................................................ [2] 06_0417_11_2023_1.9 ©UCLES20232 Describethepurposeofawebbrowser. ........................................................................................................................................... ........................................................................................................................................... ........................................................................................................................................... ...........................................................................................................................................",
          "marks": 2,
          "level": 1,
          "parentId": "1"
        },
        {
          "id": "1b",
          "text": "............................................................................................................................................... 2................................................................................................................................................ [2] 06_0417_11_2023_1.9 ©UCLES20232 Describethepurposeofawebbrowser. ........................................................................................................................................... ........................................................................................................................................... ........................................................................................................................................... ........................................................................................................................................... ........................................................................................................................................... ........................................................................................................................................... ........................................................................................................................................... ...........................................................................................................................................",
          "marks": 4,
          "level": 1,
          "parentId": "1"
        },
        {
          "id": "1a",
          "text": "............................................................................................................................................... 2................................................................................................................................................ [2] 06_0417_11_2023_1.9 ©UCLES20232 Describethepurposeofawebbrowser. ........................................................................................................................................... ........................................................................................................................................... ........................................................................................................................................... ...........................................................................................................................................",
          "marks": 2,
          "level": 1,
          "parentId": "1"
        },
        {
          "id": "1b",
          "text": "............................................................................................................................................... 2................................................................................................................................................ [2] 06_0417_11_2023_1.9 ©UCLES20232 Describethepurposeofawebbrowser. ........................................................................................................................................... ........................................................................................................................................... ........................................................................................................................................... ........................................................................................................................................... ........................................................................................................................................... ........................................................................................................................................... ........................................................................................................................................... ...........................................................................................................................................",
          "marks": 4,
          "level": 1,
          "parentId": "1"
        },
        {
          "id": "1a",
          "text": "............................................................................................................................................... 2................................................................................................................................................ [2] 06_0417_11_2023_1.9 ©UCLES20232 Describethepurposeofawebbrowser. gif...................................................................................................................................... ........................................................................................................................................... jpg..................................................................................................................................... ...........................................................................................................................................",
          "marks": 2,
          "level": 1,
          "parentId": "1"
        },
        {
          "id": "1b",
          "text": "............................................................................................................................................... 2................................................................................................................................................ [2] 06_0417_11_2023_1.9 ©UCLES20232 Describethepurposeofawebbrowser. ........................................................................................................................................... ........................................................................................................................................... ........................................................................................................................................... ........................................................................................................................................... ........................................................................................................................................... ........................................................................................................................................... ........................................................................................................................................... ........................................................................................................................................... ........................................................................................................................................... ........................................................................................................................................... ........................................................................................................................................... ...........................................................................................................................................",
          "marks": 6,
          "level": 1,
          "parentId": "1"
        },
        {
          "id": "1c",
          "text": "............................................................................................................................................... 2................................................................................................................................................ [2] 06_0417_11_2023_1.9 ©UCLES20232 Describethepurposeofawebbrowser. 1........................................................................................................................................ ........................................................................................................................................... 2........................................................................................................................................ ...........................................................................................................................................",
          "marks": 2,
          "level": 1,
          "parentId": "1"
        },
        {
          "id": "1a",
          "text": "............................................................................................................................................... 2................................................................................................................................................ [2] 06_0417_11_2023_1.9 ©UCLES20232 Describethepurposeofawebbrowser. ...........................................................................................................................................",
          "marks": 1,
          "level": 1,
          "parentId": "1"
        },
        {
          "id": "1b",
          "text": "............................................................................................................................................... 2................................................................................................................................................ [2] 06_0417_11_2023_1.9 ©UCLES20232 Describethepurposeofawebbrowser. ...........................................................................................................................................",
          "marks": 1,
          "level": 1,
          "parentId": "1"
        },
        {
          "id": "1c",
          "text": "............................................................................................................................................... 2................................................................................................................................................ [2] 06_0417_11_2023_1.9 ©UCLES20232 Describethepurposeofawebbrowser. ...........................................................................................................................................",
          "marks": 1,
          "level": 1,
          "parentId": "1"
        }
      ],
      "totalMarks": 68
    }
  ]
}